aikasilta/__init__.py
aikasilta/__main__.py
aikasilta/bridge.py
aikasilta/cli.py
test/__init__.py
test/conftest.py
test/context.py
test/test_bridge.py
test/test_cli.py
aikasilta-2022.7.24.dist-info/LICENSE
aikasilta-2022.7.24.dist-info/METADATA
aikasilta-2022.7.24.dist-info/WHEEL
aikasilta-2022.7.24.dist-info/entry_points.txt
aikasilta-2022.7.24.dist-info/top_level.txt
aikasilta-2022.7.24.dist-info/RECORD
