Metadata-Version: 2.1
Name: aikasilta
Version: 2022.7.24
Summary: Time bridge (Finnish: aikasilta) - experimental reporting bridge from the Nineties into right now.
Home-page: https://git.sr.ht/~sthagen/aikasilta
Author: Stefan Hagen
Author-email: stefan@hagen.link
Maintainer: Stefan Hagen
Maintainer-email: stefan@hagen.link
Project-URL: Bug Tracker, https://todo.sr.ht/~sthagen/aikasilta
Project-URL: Documentation, https://codes.dilettant.life/docs/aikasilta
Project-URL: Source Code, https://git.sr.ht/~sthagen/aikasilta
Keywords: developer-tools,devops
Classifier: Development Status :: 3 - Alpha
Classifier: Intended Audience :: Developers
Classifier: License :: OSI Approved :: MIT License
Classifier: Programming Language :: Python :: 3.10
Classifier: Programming Language :: Python :: 3.8
Classifier: Programming Language :: Python :: 3.9
Requires-Python: >=3.8
License-File: LICENSE
Requires-Dist: Jinja2 (>=3.1.2)
Requires-Dist: aiohttp (>=3.8.1)
Requires-Dist: asyncpg (>=0.26.0)
Requires-Dist: atlassian-python-api (>=3.25.0)
Requires-Dist: attrs (>=21.4.0)
Requires-Dist: starlette (>=0.20.4)
Requires-Dist: typer (>=0.6.1)
Requires-Dist: uplink (>=0.9.7)
Requires-Dist: websockets (>=10.3)
Provides-Extra: dev
Requires-Dist: black ; extra == 'dev'
Requires-Dist: coverage ; extra == 'dev'
Requires-Dist: flake8 ; extra == 'dev'
Requires-Dist: mypy ; extra == 'dev'
Requires-Dist: pytest ; extra == 'dev'
Requires-Dist: pytest-cov ; extra == 'dev'
Requires-Dist: pytest-flake8 ; extra == 'dev'
